greyupnp/__init__.py
greyupnp/ssdp.py
greyupnp-0.3.dist-info/DESCRIPTION.rst
greyupnp-0.3.dist-info/METADATA
greyupnp-0.3.dist-info/RECORD
greyupnp-0.3.dist-info/WHEEL
greyupnp-0.3.dist-info/metadata.json
greyupnp-0.3.dist-info/namespace_packages.txt
greyupnp-0.3.dist-info/top_level.txt
