Metadata-Version: 2.0
Name: greyupnp
Version: 0.3
Summary: Not **all** the Python UPnP tools you could ever want. But some.
Home-page: https://github.com/the-allanc/greyupnp/
Author: Allan Crooks
Author-email: allan@increment.one
License: MIT
Keywords: upnp,ssdp
Platform: UNKNOWN
Classifier: Development Status :: 4 - Beta
Classifier: Intended Audience :: Developers
Classifier: License :: OSI Approved :: MIT License
Classifier: Operating System :: OS Independent
Classifier: Programming Language :: Python :: 2.7
Classifier: Programming Language :: Python :: 3
Classifier: Topic :: Software Development :: Libraries
Classifier: Topic :: Software Development :: Libraries :: Python Modules
Requires-Python: >=2.7
Requires-Dist: crookbook (>=0.0.6)
Requires-Dist: requests
Requires-Dist: six
Provides-Extra: docs
Requires-Dist: allanc-sphinx[yeen] (>=0.2); extra == 'docs'
Requires-Dist: collective.checkdocs; extra == 'docs'
Requires-Dist: jaraco.packaging (>=3.2); extra == 'docs'
Requires-Dist: rst.linker (>=1.9); extra == 'docs'
Requires-Dist: sphinx; extra == 'docs'
Provides-Extra: testing
Requires-Dist: pytest (>=2.8); extra == 'testing'
Requires-Dist: pytest-sugar; extra == 'testing'
